__init__.py
brapi2biosamples.py
brapi2biosamples-0.1.0.dist-info/LICENSE
brapi2biosamples-0.1.0.dist-info/METADATA
brapi2biosamples-0.1.0.dist-info/WHEEL
brapi2biosamples-0.1.0.dist-info/entry_points.txt
brapi2biosamples-0.1.0.dist-info/top_level.txt
brapi2biosamples-0.1.0.dist-info/RECORD
