Metadata-Version: 2.1
Name: brapi2biosamples
Version: 0.1.0
Summary: Command Line Interface to upload data to the European Nucleotide Archive
Home-page: https://github.com/ELIXIR-Belgium/brapi2biosamples
Author: Bert Droesbeke
Author-email: bedro@vib.ugent.be
License: MIT
Keywords: pip,brapi2biosamples,cli,biosamples,upload,JSON,EBI
Platform: UNKNOWN
Classifier: Operating System :: OS Independent
Requires-Python: >=3.5
License-File: LICENSE
Requires-Dist: click
Requires-Dist: requests (==2.22.0)
Requires-Dist: pyOpenSSL
